inceptbench_new/__init__.py
inceptbench_new/__main__.py
inceptbench_new/api/__init__.py
inceptbench_new/api/dependencies.py
inceptbench_new/api/EXAMPLES.md
inceptbench_new/api/main.py
inceptbench_new/api/models.py
inceptbench_new/api/README.md
inceptbench_new/api/test_api.py
inceptbench_new/classifier/__init__.py
inceptbench_new/classifier/content_classifier.py
inceptbench_new/cli/__init__.py
inceptbench_new/cli/main.py
inceptbench_new/cli/README.md
inceptbench_new/cli/test_cli.py
inceptbench_new/config/__init__.py
inceptbench_new/config/settings.py
inceptbench_new/config/tier_scoring.py
inceptbench_new/core/__init__.py
inceptbench_new/core/input_models.py
inceptbench_new/core/processor.py
inceptbench_new/curricula/ccss_curriculum.md
inceptbench_new/decomposer/__init__.py
inceptbench_new/decomposer/content_decomposer.py
inceptbench_new/evaluators/__init__.py
inceptbench_new/evaluators/article.py
inceptbench_new/evaluators/base.py
inceptbench_new/evaluators/fiction_reading.py
inceptbench_new/evaluators/nonfiction_reading.py
inceptbench_new/evaluators/other.py
inceptbench_new/evaluators/question.py
inceptbench_new/evaluators/quiz.py
inceptbench_new/llm/__init__.py
inceptbench_new/llm/adapters/__init__.py
inceptbench_new/llm/adapters/claude_adapter.py
inceptbench_new/llm/adapters/gemini_adapter.py
inceptbench_new/llm/adapters/openai_adapter.py
inceptbench_new/llm/base.py
inceptbench_new/llm/config.py
inceptbench_new/llm/factory.py
inceptbench_new/models/__init__.py
inceptbench_new/models/article.py
inceptbench_new/models/base.py
inceptbench_new/models/content_tree.py
inceptbench_new/models/other.py
inceptbench_new/models/question.py
inceptbench_new/models/quiz.py
inceptbench_new/models/reading.py
inceptbench_new/orchestrator/__init__.py
inceptbench_new/orchestrator/evaluation_orchestrator.py
inceptbench_new/prompts/article/decomposition.txt
inceptbench_new/prompts/article/evaluation.txt
inceptbench_new/prompts/classifier.txt
inceptbench-2.3.0.dist-info/entry_points.txt
inceptbench-2.3.0.dist-info/METADATA
inceptbench-2.3.0.dist-info/WHEEL
inceptbench-2.3.0.dist-info/RECORD
