Metadata-Version: 2.4
Name: inceptbench
Version: 2.3.0
Summary: Comprehensive benchmark and evaluation framework for educational AI question generation
License: Proprietary - Copyright Trilogy Education Services
Keywords: education,evaluation,ai,questions,assessment,benchmark,edubench,scaffolding
Author: Trilogy Team
Author-email: stanislav.huseletov@trilogy.com
Requires-Python: >=3.11,<3.14
Classifier: Development Status :: 4 - Beta
Classifier: Intended Audience :: Developers
Classifier: Intended Audience :: Education
Classifier: License :: Other/Proprietary License
Classifier: Programming Language :: Python :: 3
Classifier: Programming Language :: Python :: 3.11
Classifier: Programming Language :: Python :: 3.12
Classifier: Programming Language :: Python :: 3.13
Classifier: Topic :: Education
Requires-Dist: anthropic (>=0.70.0)
Requires-Dist: click (>=8.1.7,<9.0.0)
Requires-Dist: fastapi (>=0.100.0)
Requires-Dist: google-genai (>=0.5.0)
Requires-Dist: httpx (>=0.25.0)
Requires-Dist: langchain-openai (>=0.1.0)
Requires-Dist: numpy (>=1.24.0)
Requires-Dist: openai (>=1.100.2)
Requires-Dist: opencv-python (>=4.8.0)
Requires-Dist: pandas (>=2.0.0)
Requires-Dist: pydantic (>=2.0.0)
Requires-Dist: python-dotenv (>=1.0.0)
Requires-Dist: requests (>=2.31.0,<3.0.0)
Requires-Dist: scipy (>=1.11.0)
Requires-Dist: supabase (>=2.0.0)
Requires-Dist: tiktoken (>=0.11.0)
Requires-Dist: torch (>=2.8.0)
Requires-Dist: tqdm (>=4.66.0)
Requires-Dist: transformers (>=4.55.3)
Requires-Dist: uvicorn (>=0.23.0)
Project-URL: Homepage, https://inceptbench.com
Project-URL: Repository, https://github.com/trilogy-group/inceptbench
